mindspore_gl/__init__.py
mindspore_gl/array_kernel.cpython-37m-x86_64-linux-gnu.so
mindspore_gl/array_kernel.py
mindspore_gl/memory_kernel.cpython-37m-x86_64-linux-gnu.so
mindspore_gl/memory_kernel.py
mindspore_gl/sample_kernel.cpython-37m-x86_64-linux-gnu.so
mindspore_gl/sample_kernel.py
mindspore_gl/dataloader/__init__.py
mindspore_gl/dataloader/dataloader.py
mindspore_gl/dataloader/dataset.py
mindspore_gl/dataloader/queue.py
mindspore_gl/dataloader/samplers.py
mindspore_gl/dataloader/utils.py
mindspore_gl/dataloader/_utils/__init__.py
mindspore_gl/dataloader/_utils/concurrent_fetch.py
mindspore_gl/dataloader/_utils/fetch.py
mindspore_gl/dataloader/_utils/worker.py
mindspore_gl/dataloader/shared_numpy/__init__.py
mindspore_gl/dataloader/shared_numpy/_posixshmem.cpython-37m-x86_64-linux-gnu.so
mindspore_gl/dataloader/shared_numpy/posixshmem.c
mindspore_gl/dataloader/shared_numpy/queue.py
mindspore_gl/dataloader/shared_numpy/reduction.py
mindspore_gl/dataloader/shared_numpy/shared_memory.py
mindspore_gl/dataloader/shared_numpy/shared_numpy.py
mindspore_gl/dataset/__init__.py
mindspore_gl/dataset/alchemy.py
mindspore_gl/dataset/blog_catalog.py
mindspore_gl/dataset/cora.py
mindspore_gl/dataset/enzymes.py
mindspore_gl/dataset/imdb_binary.py
mindspore_gl/dataset/mag240m.py
mindspore_gl/dataset/ppi.py
mindspore_gl/dataset/pubmed.py
mindspore_gl/dataset/reddit.py
mindspore_gl/dataset/utils.py
mindspore_gl/extensions/__init__.py
mindspore_gl/extensions/array_kernel.pyx
mindspore_gl/extensions/memory_reference_counter.pyx
mindspore_gl/extensions/sample_kernel.pyx
mindspore_gl/graph/__init__.py
mindspore_gl/graph/graph.py
mindspore_gl/graph/ops.py
mindspore_gl/graph/utils.py
mindspore_gl/nn/__init__.py
mindspore_gl/nn/gnn_cell.py
mindspore_gl/nn/conv/__init__.py
mindspore_gl/nn/conv/agnnconv.py
mindspore_gl/nn/conv/appnpconv.py
mindspore_gl/nn/conv/bgcfconv.py
mindspore_gl/nn/conv/cfconv.py
mindspore_gl/nn/conv/dotgatconv.py
mindspore_gl/nn/conv/edgeconv.py
mindspore_gl_gpu-0.1.dist-info/METADATA
mindspore_gl_gpu-0.1.dist-info/WHEEL
mindspore_gl_gpu-0.1.dist-info/top_level.txt
mindspore_gl_gpu-0.1.dist-info/RECORD
